saffronorchestrator/__init__.py
saffronorchestrator/orchestration.py
saffronorchestrator/tests/test_main.py
saffronorchestrator-0.0.26.dist-info/METADATA
saffronorchestrator-0.0.26.dist-info/WHEEL
saffronorchestrator-0.0.26.dist-info/top_level.txt
saffronorchestrator-0.0.26.dist-info/RECORD
