Metadata-Version: 2.1
Name: saffronorchestrator
Version: 0.0.26
Author: James Baker
Author-email: james@talentium.io
License: MIT
Classifier: Programming Language :: Python :: 3
Classifier: License :: OSI Approved :: MIT License
Classifier: Operating System :: OS Independent
Requires-Dist: rankexpansion >=0.0.17
Requires-Dist: searchdatamodels >=0.0.59
Requires-Dist: pymongo ==4.5.0
Requires-Dist: fastapi ==0.97.0
Requires-Dist: basilsweepercrawler >=0.0.11
Requires-Dist: nutmegredundancysolver >=0.0.13
